j2cli/__init__.py
j2cli/cli.py
j2cli/context.py
j2cli/extras/__init__.py
j2cli/extras/customize.py
j2cli/extras/filters.py
j2cli-0.3.9.dist-info/LICENSE
j2cli-0.3.9.dist-info/METADATA
j2cli-0.3.9.dist-info/WHEEL
j2cli-0.3.9.dist-info/entry_points.txt
j2cli-0.3.9.dist-info/top_level.txt
j2cli-0.3.9.dist-info/RECORD
